LICENSE
MANIFEST.in
README.rst
setup.cfg
setup.py
pyrpc/__init__.py
pyrpc/admin.py
pyrpc/apps.py
pyrpc/decorators.py
pyrpc/models.py
pyrpc/serializers.py
pyrpc/store.py
pyrpc/urls.py
pyrpc/utils.py
pyrpc/views.py
pyrpc/migrations/__init__.py
pyrpc_django.egg-info/PKG-INFO
pyrpc_django.egg-info/SOURCES.txt
pyrpc_django.egg-info/dependency_links.txt
pyrpc_django.egg-info/requires.txt
pyrpc_django.egg-info/top_level.txt
tests/__init__.py
tests/test_apps.py
tests/test_decorators.py
tests/test_serializers.py
tests/test_store.py
tests/test_utils.py
tests/test_views.py
tests/utils.py