Metadata-Version: 1.1
Name: pyrpc-django
Version: 1.0
Summary: A Django app to conduct Web-based polls.
Home-page: https://github.com/louisliv/pyrpc
Author: Louis Livingston
Author-email: livingston.louis@gmail.com
License: BSD-3-Clause  # Example license
Download-URL: https://github.com/louisliv/pyrpc/archive/0.1.tar.gz
Platform: UNKNOWN
Classifier: Environment :: Web Environment
Classifier: Framework :: Django
Classifier: Intended Audience :: Developers
Classifier: License :: OSI Approved :: BSD License
Classifier: Operating System :: OS Independent
Classifier: Programming Language :: Python
Classifier: Programming Language :: Python :: 3
Classifier: Programming Language :: Python :: 3 :: Only
Classifier: Programming Language :: Python :: 3.6
Classifier: Programming Language :: Python :: 3.7
Classifier: Programming Language :: Python :: 3.8
Classifier: Topic :: Internet :: WWW/HTTP
Classifier: Topic :: Internet :: WWW/HTTP :: Dynamic Content
